citybikes/__init__.py
citybikes/asyncio.py
citybikes/client.py
citybikes/model.py
citybikes/resource.py
citybikes/utils.py
python_citybikes-0.3.3.dist-info/licenses/LICENSE.txt
python_citybikes-0.3.3.dist-info/METADATA
python_citybikes-0.3.3.dist-info/WHEEL
python_citybikes-0.3.3.dist-info/top_level.txt
python_citybikes-0.3.3.dist-info/RECORD
