Metadata-Version: 2.4
Name: python-citybikes
Version: 0.3.3
Summary: Client interface for the Citybikes API
License-Expression: MIT
Project-URL: Homepage, https://citybik.es
Project-URL: Documentation, https://docs.citybik.es
Project-URL: Source, https://github.com/eskerda/python-citybikes
Project-URL: Tracker, https://github.com/eskerda/python-citybikes/issues
Keywords: Citybikes,api.citybik.es,bike sharing
Classifier: Development Status :: 4 - Beta
Classifier: Intended Audience :: Developers
Classifier: Programming Language :: Python
Classifier: Programming Language :: Python :: 3
Classifier: Programming Language :: Python :: 3.9
Classifier: Programming Language :: Python :: 3.10
Classifier: Programming Language :: Python :: 3.11
Classifier: Programming Language :: Python :: 3.12
Classifier: Programming Language :: Python :: 3.13
Requires-Python: >=3.9
License-File: LICENSE.txt
Requires-Dist: aiohttp
Requires-Dist: requests
Dynamic: license-file
